wzl/http/__init__.py
wzl/http/error.py
wzl/http/server.py
wzl/soil/__init__.py
wzl/soil/component.py
wzl/soil/datatype.py
wzl/soil/element.py
wzl/soil/error.py
wzl/soil/event.py
wzl/soil/function.py
wzl/soil/measurement.py
wzl/soil/parameter.py
wzl/soil/semantics.py
wzl/soil/variable.py
wzl/stream/__init__.py
wzl/stream/advertisement_job.py
wzl/stream/configurable_job.py
wzl/stream/event_job.py
wzl/stream/fixed_job.py
wzl/stream/job.py
wzl/stream/scheduler.py
wzl/stream/update_job.py
wzl/utils/__init__.py
wzl/utils/constants.py
wzl/utils/error.py
wzl/utils/logger.py
wzl/utils/resources.py
wzl/utils/serialize.py
wzl_udi-10.1.5.dist-info/licenses/LICENSE
wzl_udi-10.1.5.dist-info/METADATA
wzl_udi-10.1.5.dist-info/WHEEL
wzl_udi-10.1.5.dist-info/top_level.txt
wzl_udi-10.1.5.dist-info/RECORD
