Metadata-Version: 2.4
Name: wzl-udi
Version: 10.1.5
Summary: Provides REST-server, publisher-interface and serializer for the Unified Device Interface in Python based on the SensOr Interfacing Language (SOIL).
Home-page: https://git-ce.rwth-aachen.de/wzl-mq-public/soil/python
Author: Matthias Bodenbenner
Author-email: m.bodenbenner@wzl-mq.rwth-aachen.de
Project-URL: Bug Tracker, https://git-ce.rwth-aachen.de/wzl-mq-public/soil/python/-/issues
Classifier: Programming Language :: Python :: 3
Classifier: License :: OSI Approved :: MIT License
Classifier: Operating System :: OS Independent
License-File: LICENSE
Requires-Dist: aiohttp~=3.13.0
Requires-Dist: Deprecated~=1.2.13
Requires-Dist: nest-asyncio~=1.5.6
Requires-Dist: pytz==2024.1
Requires-Dist: wzl-mqtt~=2.6.1
Requires-Dist: rdflib~=7.0.0
Dynamic: author
Dynamic: author-email
Dynamic: classifier
Dynamic: description
Dynamic: description-content-type
Dynamic: home-page
Dynamic: license-file
Dynamic: project-url
Dynamic: requires-dist
Dynamic: summary
